markdown_fenced_code_tabs/__init__.py
markdown_fenced_code_tabs/base-template.html
markdown_fenced_code_tabs/bootstrap3-template.html
markdown_fenced_code_tabs/bootstrap4-template.html
markdown_fenced_code_tabs/default-template.html
markdown_fenced_code_tabs/tab.py
markdown_fenced_code_tabs/util.py
markdown_fenced_code_tabs-1.0.5.dist-info/LICENSE
markdown_fenced_code_tabs-1.0.5.dist-info/METADATA
markdown_fenced_code_tabs-1.0.5.dist-info/WHEEL
markdown_fenced_code_tabs-1.0.5.dist-info/top_level.txt
markdown_fenced_code_tabs-1.0.5.dist-info/RECORD
