Metadata-Version: 2.1
Name: markdown-fenced-code-tabs
Version: 1.0.5
Summary: Generates a html structure for consecutive fenced code blocks content
Home-page: https://github.com/yacir/markdown-fenced-code-tabs
Author: Yassir Barchi
Author-email: github@yassir.fr
License: MIT
Project-URL: Bug Reports, https://github.com/yacir/markdown-fenced-code-tabs/issues
Project-URL: Say Thanks!, http://saythanks.io/to/yacir
Project-URL: Source, https://github.com/yacir/markdown-fenced-code-tabs
Keywords: fenced code blocks,code,fenced,tabs,mkdocs,markdown
Platform: UNKNOWN
Classifier: License :: OSI Approved :: MIT License
Classifier: Operating System :: OS Independent
Classifier: Programming Language :: Python
Classifier: Programming Language :: Python :: 2
Classifier: Programming Language :: Python :: 3
Classifier: Intended Audience :: Developers
Classifier: Topic :: Software Development :: Libraries
Classifier: Topic :: Text Processing
Requires-Dist: markdown (>=2.6)
Requires-Dist: htmlmin (>=0.1.12)
Requires-Dist: Jinja2 (>=2.7.1)
